firstmodulejeremylaitter/__init__.py
firstmodulejeremylaitter/add.py
firstmodulejeremylaitter/subtract.py
firstmodulejeremylaitter/extras/__init__.py
firstmodulejeremylaitter/extras/divide.py
firstmodulejeremylaitter/extras/multiply.py
firstmodulejeremylaitter-0.0.4.dist-info/METADATA
firstmodulejeremylaitter-0.0.4.dist-info/WHEEL
firstmodulejeremylaitter-0.0.4.dist-info/top_level.txt
firstmodulejeremylaitter-0.0.4.dist-info/RECORD
